mikes_verysimplemodule/__init__.py
mikes_verysimplemodule/add.py
mikes_verysimplemodule/subtract.py
mikes_verysimplemodule/extras/__init__.py
mikes_verysimplemodule/extras/divide.py
mikes_verysimplemodule/extras/multiply.py
verysimplemodule/__init__.py
verysimplemodule/add.py
verysimplemodule/subtract.py
verysimplemodule/extras/__init__.py
verysimplemodule/extras/divide.py
verysimplemodule/extras/multiply.py
mikes_verysimplemodule-0.0.3.dist-info/METADATA
mikes_verysimplemodule-0.0.3.dist-info/WHEEL
mikes_verysimplemodule-0.0.3.dist-info/top_level.txt
mikes_verysimplemodule-0.0.3.dist-info/RECORD
