Metadata-Version: 2.1
Name: mikes_verysimplemodule
Version: 0.0.3
Summary: My first Python package
Author: Mike
Author-email: elee353@aucklanduni.ac.nz
Keywords: python,first package
Classifier: Development Status :: 3 - Alpha
Classifier: Intended Audience :: Education
Classifier: Programming Language :: Python :: 2
Classifier: Programming Language :: Python :: 3
Classifier: Operating System :: MacOS :: MacOS X
Classifier: Operating System :: Microsoft :: Windows
